README.md
setup.py
spacy_canonicalizer/DatabaseConnection.py
spacy_canonicalizer/EntityCandidates.py
spacy_canonicalizer/EntityClassifier.py
spacy_canonicalizer/EntityCollection.py
spacy_canonicalizer/EntityElement.py
spacy_canonicalizer/EntityLinker.py
spacy_canonicalizer/TermCandidate.py
spacy_canonicalizer/TermCandidateExtractor.py
spacy_canonicalizer/__init__.py
spacy_canonicalizer/__main__.py
spacy_canonicalizer.egg-info/PKG-INFO
spacy_canonicalizer.egg-info/SOURCES.txt
spacy_canonicalizer.egg-info/dependency_links.txt
spacy_canonicalizer.egg-info/entry_points.txt
spacy_canonicalizer.egg-info/requires.txt
spacy_canonicalizer.egg-info/top_level.txt
spacy_canonicalizer.egg-info/zip-safe