Metadata-Version: 2.1
Name: spacy-canonicalizer
Version: 1.0.2
Summary: Entity and Relationship Caninicalization Pipeline for spaCy
Home-page: https://github.com/nu-c3lab/spaCy-canonicalizer
Author: C3 Lab
Author-email: cameron.barrie@u.northwestern.edu
License: MIT
Platform: UNKNOWN
Classifier: Environment :: Console
Classifier: Intended Audience :: Developers
Classifier: Intended Audience :: Science/Research
Classifier: License :: OSI Approved :: MIT License
Classifier: Programming Language :: Cython
Classifier: Programming Language :: Python
Classifier: Programming Language :: Python :: 3.6
